memory/rom.v
module rom #(parameter MEM_SIZE = 6, parameter DATA_W = 10)(
	 input 					   clk,
	 input 				       write,
	 input 					   read,
     input [MEM_SIZE - 1:0]    addr_w,
     input [MEM_SIZE - 1:0]    addr_r,
     input [DATA_W - 1:0]      datain,

     output reg [DATA_W - 1:0] dataout
);
    

reg [DATA_W - 1:0]mem[2**MEM_SIZE - 1:0] ;

always @(posedge clk) begin
	if (read)  dataout <= mem[addr_r] ;
	if (write) mem[addr_w] <= datain ;
end

endmodule

memory/testbench.v
`timescale 1 ns / 100 ps

module testbench();

reg clk = 1'b0; // Represents clock, initial value is 0 

always begin
    #1 clk = ~clk; // Toggle clock every 1ns 
end

reg  write = 1'b1;
reg  read =  1'b0;

reg  [5:0]addr_w = 6'h0;
reg  [5:0]addr_r = 6'h0;

reg  [9:0]d = 10'd12; //input  data 
wire [9:0]q;          //output data  //mem[0]: 12 -> | 12 | -> x

rom #(.MEM_SIZE(6), .DATA_W(10)) rom(.clk(clk), .write(write), .read(read), .addr_w(addr_w), .addr_r(addr_r), .datain(d), .dataout(q));


initial begin
    $dumpvars;      // Open for dump of signals
    $display("Test started...");   // Write to console 
    #2 write = 1'b0; read =  1'b1; addr_w = 6'h0; addr_r = 6'h0; d = 10'd13; //mem[0]: 13 -> | 12 | -> 12
    #2 write = 1'b1; read =  1'b0; addr_w = 6'h0; addr_r = 6'h0; d = 10'd14; //mem[0]: 14 -> | 14 | -> 12
  	#2 write = 1'b0; read =  1'b1; addr_w = 6'h0; addr_r = 6'h0; d = 10'd15; //mem[0]: 15 -> | 14 | -> 14 
  	#2 write = 1'b1; read =  1'b0; addr_w = 6'h1; addr_r = 6'h1; d = 10'd36; //mem[1]: 36 -> | 36 | -> 14
  	#2 write = 1'b0; read =  1'b1; addr_w = 6'h1; addr_r = 6'h1; d = 10'd37; //mem[1]: 37 -> | 36 | -> 36 
  	#2 write = 1'b1; read =  1'b1; addr_w = 6'h1; addr_r = 6'h1; d = 10'd38; //mem[1]: 38 -> | 38 | -> 36 !!!R=1 & W=1 
  	#2 write = 1'b0; read =  1'b1; addr_w = 6'h1; addr_r = 6'h1; d = 10'd39; //mem[1]: 39 -> | 38 | -> 38  
    #40 $finish;    // Stop simulation
end

endmodule

memory/dump.vcd
$date
	Sun Mar 31 22:40:16 2024
$end
$version
	Icarus Verilog
$end
$timescale
	100ps
$end
$scope module testbench $end
$var wire 10 ! q [9:0] $end
$var reg 6 " addr_r [5:0] $end
$var reg 6 # addr_w [5:0] $end
$var reg 1 $ clk $end
$var reg 10 % d [9:0] $end
$var reg 1 & read $end
$var reg 1 ' write $end
$scope module rom $end
$var wire 6 ( addr_r [5:0] $end
$var wire 6 ) addr_w [5:0] $end
$var wire 1 $ clk $end
$var wire 10 * datain [9:0] $end
$var wire 1 & read $end
$var wire 1 ' write $end
$var reg 10 + dataout [9:0] $end
$upscope $end
$upscope $end
$enddefinitions $end
#0
$dumpvars
bx +
b1100 *
b0 )
b0 (
1'
0&
b1100 %
0$
b0 #
b0 "
bx !
$end
#10
1$
#20
0$
b1101 %
b1101 *
1&
0'
#30
b1100 !
b1100 +
1$
#40
0$
b1110 %
b1110 *
0&
1'
#50
1$
#60
0$
b1111 %
b1111 *
1&
0'
#70
b1110 !
b1110 +
1$
#80
0$
b100100 %
b100100 *
b1 "
b1 (
b1 #
b1 )
0&
1'
#90
1$
#100
0$
b100101 %
b100101 *
1&
0'
#110
b100100 !
b100100 +
1$
#120
0$
b100110 %
b100110 *
1'
#130
1$
#140
0$
b100111 %
b100111 *
0'
#150
b100110 !
b100110 +
1$
